{
  "schema_version": "1.4.0",
  "id": "GHSA-2c7v-qcjp-4mg2",
  "modified": "2022-12-14T21:42:00Z",
  "published": "2022-12-14T21:42:00Z",
  "aliases": [
    "CVE-2022-41089"
  ],
  "summary": ".NET Remote Code Execution Vulnerability",
  "details": "# Microsoft Security Advisory CVE-2022-41089: .NET Remote Code Execution Vulnerability\n\n## <a name=\"executive-summary\"></a>Executive summary\n\nMicrosoft is releasing this security advisory to provide information about a vulnerability in .NET Core 3.1, .NET 6.0., and .NET 7.0. This advisory also provides guidance on what developers can do to update their applications to remove this vulnerability.\n\nA remote code execution vulnerability exists in .NET Core 3.1, .NET 6.0, and .NET 7.0, where a malicious actor could cause a user to run arbitrary code as a result of parsing maliciously crafted xps files.\n\n## Announcement\n\nAnnouncement for this issue can be found at https://github.com/dotnet/announcements/issues/242\n\n### <a name=\"mitigation-factors\"></a>Mitigation factors\n\nMicrosoft has not identified any mitigating factors for this vulnerability.\n\n## <a name=\"affected-software\"></a>Affected software\n\n* Any .NET 7.0 WinForms or WPF application running on .NET 7.0.0 or earlier.\n* Any .NET 6.0 WinForms or WPF application running on .NET 6.0.11 or earlier.\n* Any .NET Core 3.1 WinForms or WPF application running on .NET 3.1.31 or earlier.\n\nIf the application does not utilize WinForms or WPF, it is not affected by this vulnerability.\n\nApplications targeting Mac, Linux, Android, iOS, and other non-Windows platforms are not affected by this vulnerability.\n\nIf your application uses the following package versions, ensure you update to the latest version of .NET.\n\n### <a name=\".NET Core 3.1\"></a>.NET Core 3.1\n\nPackage name | Affected version | Patched version\n------------ | ---------------- | -------------------------\n[Microsoft.WindowsDesktop.App.Runtime.win-x64](https://www.nuget.org/packages/Microsoft.WindowsDesktop.App.Runtime.win-x64)|>= 3.1.0, <= 3.1.31|3.1.32\n[Microsoft.WindowsDesktop.App.Runtime.win-x86](https://www.nuget.org/packages/Microsoft.WindowsDesktop.App.Runtime.win-x86)|>= 3.1.0, <= 3.1.31|3.1.32\n\n### <a name=\".NET 6\"></a>.NET 6\n\nPackage name | Affected version | Patched version\n------------ | ---------------- | -------------------------\n[Microsoft.WindowsDesktop.App.Runtime.win-arm64](https://www.nuget.org/packages/Microsoft.WindowsDesktop.App.Runtime.win-arm64)|>= 6.0.0, <= 6.0.11|6.0.12\n[Microsoft.WindowsDesktop.App.Runtime.win-x64](https://www.nuget.org/packages/Microsoft.WindowsDesktop.App.Runtime.win-x64)|>= 6.0.0, <= 6.0.11|6.0.12\n[Microsoft.WindowsDesktop.App.Runtime.win-x86](https://www.nuget.org/packages/Microsoft.WindowsDesktop.App.Runtime.win-x86)|>= 6.0.0, <= 6.0.11|6.0.12\n\n### <a name=\".NET 7\"></a>.NET 7\n\nPackage name | Affected version | Patched version\n------------ | ---------------- | -------------------------\n[Microsoft.WindowsDesktop.App.Runtime.win-arm64](https://www.nuget.org/packages/Microsoft.WindowsDesktop.App.Runtime.win-arm64)|>= 7.0.0, <= 7.0.0|7.0.1\n[Microsoft.WindowsDesktop.App.Runtime.win-x64](https://www.nuget.org/packages/Microsoft.WindowsDesktop.App.Runtime.win-x64)|>= 7.0.0, <= 7.0.0|7.0.1\n[Microsoft.WindowsDesktop.App.Runtime.win-x86](https://www.nuget.org/packages/Microsoft.WindowsDesktop.App.Runtime.win-x86)|>= 7.0.0, <= 7.0.0|7.0.1\n\n## Advisory FAQ\n\n### <a name=\"how-affected\"></a>How do I know if I am affected?\n\nIf you have a runtime or SDK with a version listed, or an affected package listed in [affected software](#affected-software), you're exposed to the vulnerability.\n\n### <a name=\"how-fix\"></a>How do I fix the issue?\n\n* To fix the issue please install the latest version of .NET 7.0, .NET 6.0 or .NET Core 3.1. If you have installed one or more .NET SDKs through Visual Studio, Visual Studio will prompt you to update Visual Studio, which will also update your .NET  SDKs.\n* If you have .NET Core 3.1 or greater installed, you can list the versions you have installed by running the `dotnet --info` command. You will see output like the following;\n* If you are using one of the affected packages, please update to the patched version listed above. \n\n```\n.NET Core SDK (reflecting any global.json):\n\n Version:   6.0.300\n Commit:    8473146e7d\n\nRuntime Environment:\n\n OS Name:     Windows\n OS Version:  10.0.18363\n OS Platform: Windows\n RID:         win10-x64\n Base Path:   C:\\Program Files\\dotnet\\sdk\\6.0.300\\\n\nHost (useful for support):\n\n  Version: 6.0.5\n  Commit:  8473146e7d\n\n.NET Core SDKs installed:\n\n  6.0.300 [C:\\Program Files\\dotnet\\sdk]\n\n.NET Core runtimes installed:\n\n  Microsoft.AspNetCore.App 6.0.5 [C:\\Program Files\\dotnet\\shared\\Microsoft.AspNetCore.App]\n  Microsoft.NETCore.App 6.0.5 [C:\\Program Files\\dotnet\\shared\\Microsoft.NETCore.App]\n  Microsoft.WindowsDesktop.App 6.0.5 [C:\\Program Files\\dotnet\\shared\\Microsoft.WindowsDesktop.App]\n\nTo install additional .NET Core runtimes or SDKs:\n  https://aka.ms/dotnet-download\n```\n\n* If you're using .NET 7.0, you should download and install Runtime 7.0.1 or SDK 7.0.101 (for Visual Studio 2022 v17.4) from https://dotnet.microsoft.com/download/dotnet-core/7.0.\n* If you're using .NET 6.0, you should download and install Runtime 6.0.12 or SDK 6.0.112 (for Visual Studio 2022 v17.1) from https://dotnet.microsoft.com/download/dotnet-core/6.0.\n* If you're using .NET Core 3.1, you should download and install Runtime 3.1.32 (for Visual Studio 2019 v16.9) from https://dotnet.microsoft.com/download/dotnet-core/3.1.\n\n.NET 7.0, .NET 6.0 and .NET Core 3.1 updates are also available from Microsoft Update. To access this either type \"Check for updates\" in your Windows search, or open Settings, choose Update & Security and then click Check for Updates.\n\nOnce you have installed the updated runtime or SDK, restart your apps for the update to take effect.\n\nAdditionally, if you've deployed [self-contained applications](https://docs.microsoft.com/dotnet/core/deploying/#self-contained-deployments-scd) targeting any of the impacted versions, these applications are also vulnerable and must be recompiled and redeployed.\n\n## Other Information\n\n### Acknowledgements\n\n[Eleftherios Panos](https://twitter.com/lefterispan) with [Nettitude](https://www.nettitude.com/)\n[Nick Landers](https://twitter.com/monoxgas) with NetSPI\n\n### Reporting Security Issues\n\nIf you have found a potential security issue in .NET 7.0, .NET 6.0 or .NET Core 3.1, please email details to secure@microsoft.com. Reports may qualify for the Microsoft .NET Core & .NET 5 Bounty. Details of the Microsoft .NET Bounty Program including terms and conditions are at <https://aka.ms/corebounty>.\n\n### Support\n\nYou can ask questions about this issue on GitHub in the .NET GitHub organization. The main repos are located at https://github.com/dotnet/runtime and https://github.com/dotnet/wpf/. The Announcements repo (https://github.com/dotnet/Announcements) will contain this bulletin as an issue and will include a link to a discussion issue. You can ask questions in the linked discussion issue.\n\n### Disclaimer\n\nThe information provided in this advisory is provided \"as is\" without warranty of any kind. Microsoft disclaims all warranties, either express or implied, including the warranties of merchantability and fitness for a particular purpose. In no event shall Microsoft Corporation or its suppliers be liable for any damages whatsoever including direct, indirect, incidental, consequential, loss of business profits or special damages, even if Microsoft Corporation or its suppliers have been advised of the possibility of such damages. Some states do not allow the exclusion or limitation of liability for consequential or incidental damages so the foregoing limitation may not apply.\n\n### External Links\n\n[CVE-2022-41089]( https://www.cve.org/CVERecord?id=CVE-2022-41089)\n\n",
  "severity": [

  ],
  "affected": [
    {
      "package": {
        "ecosystem": "NuGet",
        "name": "Microsoft.WindowsDesktop.App.Runtime.win-x64"
      },
      "ranges": [
        {
          "type": "ECOSYSTEM",
          "events": [
            {
              "introduced": "3.1.0"
            },
            {
              "fixed": "3.1.32"
            }
          ]
        }
      ],
      "database_specific": {
        "last_known_affected_version_range": "<= 3.1.31"
      }
    },
    {
      "package": {
        "ecosystem": "NuGet",
        "name": "Microsoft.WindowsDesktop.App.Runtime.win-x86"
      },
      "ranges": [
        {
          "type": "ECOSYSTEM",
          "events": [
            {
              "introduced": "3.1.0"
            },
            {
              "fixed": "3.1.32"
            }
          ]
        }
      ],
      "database_specific": {
        "last_known_affected_version_range": "<= 3.1.31"
      }
    },
    {
      "package": {
        "ecosystem": "NuGet",
        "name": "Microsoft.WindowsDesktop.App.Runtime.win-arm64"
      },
      "ranges": [
        {
          "type": "ECOSYSTEM",
          "events": [
            {
              "introduced": "6.0.0"
            },
            {
              "fixed": "6.0.12"
            }
          ]
        }
      ],
      "database_specific": {
        "last_known_affected_version_range": "<= 6.0.11"
      }
    },
    {
      "package": {
        "ecosystem": "NuGet",
        "name": "Microsoft.WindowsDesktop.App.Runtime.win-x64"
      },
      "ranges": [
        {
          "type": "ECOSYSTEM",
          "events": [
            {
              "introduced": "6.0.0"
            },
            {
              "fixed": "6.0.12"
            }
          ]
        }
      ],
      "database_specific": {
        "last_known_affected_version_range": "<= 6.0.11"
      }
    },
    {
      "package": {
        "ecosystem": "NuGet",
        "name": "Microsoft.WindowsDesktop.App.Runtime.win-x86"
      },
      "ranges": [
        {
          "type": "ECOSYSTEM",
          "events": [
            {
              "introduced": "6.0.0"
            },
            {
              "fixed": "6.0.12"
            }
          ]
        }
      ],
      "database_specific": {
        "last_known_affected_version_range": "<= 6.0.11"
      }
    },
    {
      "package": {
        "ecosystem": "NuGet",
        "name": "Microsoft.WindowsDesktop.App.Runtime.win-arm64"
      },
      "ranges": [
        {
          "type": "ECOSYSTEM",
          "events": [
            {
              "introduced": "7.0.0"
            },
            {
              "fixed": "7.0.1"
            }
          ]
        }
      ],
      "versions": [
        "7.0.0"
      ]
    },
    {
      "package": {
        "ecosystem": "NuGet",
        "name": "Microsoft.WindowsDesktop.App.Runtime.win-x86"
      },
      "ranges": [
        {
          "type": "ECOSYSTEM",
          "events": [
            {
              "introduced": "7.0.0"
            },
            {
              "fixed": "7.0.1"
            }
          ]
        }
      ],
      "versions": [
        "7.0.0"
      ]
    },
    {
      "package": {
        "ecosystem": "NuGet",
        "name": "Microsoft.WindowsDesktop.App.Runtime.win-x64"
      },
      "ranges": [
        {
          "type": "ECOSYSTEM",
          "events": [
            {
              "introduced": "7.0.0"
            },
            {
              "fixed": "7.0.1"
            }
          ]
        }
      ],
      "versions": [
        "7.0.0"
      ]
    }
  ],
  "references": [
    {
      "type": "WEB",
      "url": "https://github.com/dotnet/wpf/security/advisories/GHSA-2c7v-qcjp-4mg2"
    },
    {
      "type": "WEB",
      "url": "https://github.com/dotnet/announcements/issues/242"
    },
    {
      "type": "PACKAGE",
      "url": "https://github.com/dotnet/wpf"
    },
    {
      "type": "WEB",
      "url": "https://portal.msrc.microsoft.com/en-US/security-guidance/advisory/CVE-2022-41089"
    }
  ],
  "database_specific": {
    "cwe_ids": [
      "CWE-94"
    ],
    "severity": "CRITICAL",
    "github_reviewed": true,
    "github_reviewed_at": "2022-12-14T21:42:00Z",
    "nvd_published_at": null
  }
}